bustools/__init__.py
bustools/__main__.py
bustools/adapters/__init__.py
bustools/adapters/aardvark.py
bustools/devices/__init__.py
bustools/devices/ina219.py
bustools/devices/lm75.py
bustools/devices/pca95xx.py
bustools/platforms/__init__.py
bustools/platforms/totalphase/__init__.py
bustools/platforms/totalphase/tp240310.py
bustools-0.1.0.dev2.dist-info/DESCRIPTION.rst
bustools-0.1.0.dev2.dist-info/METADATA
bustools-0.1.0.dev2.dist-info/metadata.json
bustools-0.1.0.dev2.dist-info/RECORD
bustools-0.1.0.dev2.dist-info/top_level.txt
bustools-0.1.0.dev2.dist-info/WHEEL
