Metadata-Version: 2.0
Name: bustools
Version: 0.1.0.dev2
Summary: Python tools for electrical busses
Home-page: https://github.com/FlyingCampDesign/bustools.git
Author: Flying Camp Design
Author-email: support@flyingcampdesign.com
License: MIT
Keywords: development embedded I2C SPI
Platform: UNKNOWN
Classifier: Development Status :: 2 - Pre-Alpha
Classifier: Intended Audience :: Developers
Classifier: License :: OSI Approved :: MIT License
Classifier: Programming Language :: Python :: 2
Classifier: Programming Language :: Python :: 2.7
Classifier: Topic :: Software Development :: Embedded Systems
Provides-Extra: aardvark
Requires-Dist: aardvark-py; extra == 'aardvark'
